meowcode/SerialCom.py
meowcode/__init__.py
meowcode/meowcode.py
meowcode/pyboard.py
meowcode-0.1.0.dist-info/LICENSE
meowcode-0.1.0.dist-info/METADATA
meowcode-0.1.0.dist-info/WHEEL
meowcode-0.1.0.dist-info/top_level.txt
meowcode-0.1.0.dist-info/RECORD
