Metadata-Version: 2.1
Name: meowcode
Version: 0.1.0
Summary: Lib for meowcode, build over ampy from adafruit
Home-page: https://gitee.com/KittenTech/pylib_meowcode
Author: riven
Author-email: riven@kittenbot.cc
License: MIT
Keywords: meowcode
Platform: UNKNOWN
Requires-Dist: pyserial
Requires-Dist: usb
